Beihang991ShujujiegouYuCYuyan19982015Zhenti/README.md
Beihang991ShujujiegouYuCYuyan19982015Zhenti/__init__.py
Beihang991ShujujiegouYuCYuyan19982015Zhenti/__main__.py
Beihang991ShujujiegouYuCYuyan19982015Zhenti/file.pdf
Beihang991ShujujiegouYuCYuyan19982015Zhenti/index.html
beihang_991_shujujiegou_yu_c_yuyan_1998_2015_zhenti-2024.3.2.0.dist-info/METADATA
beihang_991_shujujiegou_yu_c_yuyan_1998_2015_zhenti-2024.3.2.0.dist-info/WHEEL
beihang_991_shujujiegou_yu_c_yuyan_1998_2015_zhenti-2024.3.2.0.dist-info/entry_points.txt
beihang_991_shujujiegou_yu_c_yuyan_1998_2015_zhenti-2024.3.2.0.dist-info/top_level.txt
beihang_991_shujujiegou_yu_c_yuyan_1998_2015_zhenti-2024.3.2.0.dist-info/RECORD
